razel/__init__.py
razel/razel.py
razel-0.5.6.dist-info/METADATA
razel-0.5.6.dist-info/WHEEL
razel-0.5.6.dist-info/licenses/LICENSE.md
razel-0.5.6.dist-info/RECORD
