Metadata-Version: 2.4
Name: razel
Version: 0.5.6
Summary: a command executor with caching for data processing pipelines
Project-URL: Homepage, https://github.com/reu-dev/razel
Project-URL: Bug Tracker, https://github.com/reu-dev/razel/issues
Author-email: Stefan Reuschl <stefan@reu-dev.de>, Kacper Sagnowski <ksagnowski@gmail.com>
License-File: LICENSE.md
Classifier: License :: OSI Approved :: MIT License
Classifier: Operating System :: OS Independent
Classifier: Programming Language :: Python :: 3
Requires-Python: >=3.8
